compcor/__init__.py
compcor/corpus_metrics.py
compcor/example.py
compcor/text_embedder.py
compcor/text_tokenizer_embedder.py
compcor/utils.py
compcor-1.0.6.dist-info/LICENSE
compcor-1.0.6.dist-info/METADATA
compcor-1.0.6.dist-info/WHEEL
compcor-1.0.6.dist-info/top_level.txt
compcor-1.0.6.dist-info/RECORD
