Metadata-Version: 2.1
Name: compcor
Version: 1.0.6
Summary: Corpus level similarity measures.
Home-page: https://github.com/IBM/comparing-corpora
Author: Language and Conversation, IBM Research AI
License: Apache Software License, Version 2.0, http://www.apache.org/licenses/LICENSE-2.0
Keywords: Text Compare Corpus Metrics Measure Similarity
Platform: UNKNOWN
Classifier: Programming Language :: Python :: 3
Classifier: Operating System :: OS Independent
Requires-Python: >=3.8
License-File: LICENSE
Requires-Dist: numpy (==1.23.0)
Requires-Dist: scipy (==1.9.0)
Requires-Dist: scikit-learn (==1.1.1)
Requires-Dist: prdc
Requires-Dist: mauve-text
Requires-Dist: sentence-transformers (==2.2.1)
